broker.py
broker_cli-0.0.3.dist-info/METADATA
broker_cli-0.0.3.dist-info/RECORD
broker_cli-0.0.3.dist-info/WHEEL
broker_cli-0.0.3.dist-info/entry_points.txt
broker_cli-0.0.3.dist-info/top_level.txt
