Metadata-Version: 2.1
Name: broker-cli
Version: 0.0.3
Summary: Executing scripts on a remote broker-shell
Home-page: http://blacktre.es
Author: Johannes Daniel Nuemm
Author-email: daniel.nuemm@blacktre.es
License: MIT
Platform: UNKNOWN
